CredentialManagement/CredentialManagement.py
CredentialManagement/__init__.py
CredentialManagement-0.0.1.dist-info/METADATA
CredentialManagement-0.0.1.dist-info/WHEEL
CredentialManagement-0.0.1.dist-info/top_level.txt
CredentialManagement-0.0.1.dist-info/RECORD
