Metadata-Version: 2.1
Name: CredentialManagement
Version: 0.0.1
Summary: A small tool for handling credentials within the guyyatsu.me system.
Author-email: Hunter Dale <guyyatsu@gmail.com>
Project-URL: Homepage, https://github.com/guyyatsu/Credential-Validation/tree/master/CredentialManagement
Project-URL: Bug Tracker, https://github.com/Credential-Validation/issues
Classifier: Programming Language :: Python :: 3
Classifier: License :: OSI Approved :: MIT License
Classifier: Operating System :: OS Independent
Requires-Python: >=3.10
Requires-Dist: CryptographyMethods
